odoo/addons/stock_picking_completion_info/README.rst
odoo/addons/stock_picking_completion_info/__init__.py
odoo/addons/stock_picking_completion_info/__manifest__.py
odoo/addons/stock_picking_completion_info/i18n/stock_picking_completion_info.pot
odoo/addons/stock_picking_completion_info/models/__init__.py
odoo/addons/stock_picking_completion_info/models/stock_picking.py
odoo/addons/stock_picking_completion_info/readme/CONTRIBUTORS.rst
odoo/addons/stock_picking_completion_info/readme/DESCRIPTION.rst
odoo/addons/stock_picking_completion_info/static/description/icon.png
odoo/addons/stock_picking_completion_info/static/description/index.html
odoo/addons/stock_picking_completion_info/tests/__init__.py
odoo/addons/stock_picking_completion_info/tests/test_stock_picking_completion_info.py
odoo/addons/stock_picking_completion_info/views/stock_picking.xml
odoo13_addon_stock_picking_completion_info-13.0.1.1.0.dist-info/METADATA
odoo13_addon_stock_picking_completion_info-13.0.1.1.0.dist-info/WHEEL
odoo13_addon_stock_picking_completion_info-13.0.1.1.0.dist-info/top_level.txt
odoo13_addon_stock_picking_completion_info-13.0.1.1.0.dist-info/RECORD
